pymlutils/__init__.py
pymlutils/pymlutils.py
pymlutils/yolo.py
pymlutils-1.1.4.dist-info/METADATA
pymlutils-1.1.4.dist-info/WHEEL
pymlutils-1.1.4.dist-info/top_level.txt
pymlutils-1.1.4.dist-info/RECORD
