Metadata-Version: 2.1
Name: pymlutils
Version: 1.1.4
Summary: Various functions useful for python and machine learning. Keep your code clean.
Home-page: https://gitlab.com/baka-san/pymlutils
Author: Grant Backes
Author-email: gsbackes@gmail.com
License: UNKNOWN
Platform: UNKNOWN
Classifier: Programming Language :: Python :: 3.6
Requires-Dist: Pillow
